cafe/__init__.py
cafe/data_pipeline.py
cafe/explorer.py
cafe/feature_engineer.py
cafe/performance_validator.py
cafe/preprocessor.py
cafe/report_datapipeline.py
cafe/report_visualizer.py
cafe/tests/__init__.py
cafe/utils/__init__.py
cafe_autofe-0.1.3.dist-info/LICENSE
cafe_autofe-0.1.3.dist-info/METADATA
cafe_autofe-0.1.3.dist-info/WHEEL
cafe_autofe-0.1.3.dist-info/top_level.txt
cafe_autofe-0.1.3.dist-info/RECORD
